llmlite/__init__.py
llmlite/apis/__init__.py
llmlite/apis/chatllm.py
llmlite/backends/__init__.py
llmlite/backends/backend.py
llmlite/backends/hf_backend.py
llmlite/backends/vllm_backend.py
llmlite/consts.py
llmlite/llms/__init__.py
llmlite/llms/baichuan.py
llmlite/llms/chatglm.py
llmlite/llms/chatgpt.py
llmlite/llms/llama.py
llmlite/llms/llm.py
llmlite/llms/messages.py
llmlite/llms/model.py
llmlite/utils/__init__.py
llmlite/utils/log.py
llmlite/utils/util.py
llmlite-0.0.15.dist-info/LICENSE
llmlite-0.0.15.dist-info/METADATA
llmlite-0.0.15.dist-info/WHEEL
llmlite-0.0.15.dist-info/RECORD
