Metadata-Version: 2.1
Name: llmlite
Version: 0.0.15
Summary: A library helps to chat with all kinds of LLMs consistently.
License: MIT
Author: InftyAI
Requires-Python: >=3.10,<4.0
Classifier: License :: OSI Approved :: MIT License
Classifier: Programming Language :: Python :: 3
Classifier: Programming Language :: Python :: 3.10
Classifier: Programming Language :: Python :: 3.11
Requires-Dist: accelerate (==0.22.0)
Requires-Dist: openai (>=0.28.0,<0.29.0)
Requires-Dist: pydantic (<2)
Requires-Dist: sentencepiece (==0.1.99)
Requires-Dist: tokenizers (==0.14)
Requires-Dist: torch (>=2.1.1,<3.0.0)
Requires-Dist: transformers (==4.34.0)
Requires-Dist: vllm (==0.2.3)
